helper/__init__.py
helper/config.py
helper/controller.py
helper/parser.py
helper/setupext.py
helper/unix.py
helper/windows.py
helper-2.4.2.dist-info/zip-safe
helper-2.4.2.dist-info/top_level.txt
helper-2.4.2.dist-info/entry_points.txt
helper-2.4.2.dist-info/METADATA
helper-2.4.2.dist-info/DESCRIPTION.rst
helper-2.4.2.dist-info/metadata.json
helper-2.4.2.dist-info/WHEEL
helper-2.4.2.dist-info/RECORD
